teams_alert/__init__.py
teams_alert/send_card.py
teams_alert/templates.py
teams_alert-0.2.0.dist-info/LICENSE
teams_alert-0.2.0.dist-info/METADATA
teams_alert-0.2.0.dist-info/WHEEL
teams_alert-0.2.0.dist-info/top_level.txt
teams_alert-0.2.0.dist-info/RECORD
