Metadata-Version: 2.1
Name: teams_alert
Version: 0.2.0
Summary: A simple package to send messages or alerts to MS Teams channels.
Author-email: Andrew Pruet <japruet@gmail.com>
License: The MIT License (MIT)
Project-URL: Homepage, https://github.com/jimbo-p/teams_alert
Project-URL: Bug Tracker, https://github.com/jimbo-p/teams_alert/issues
Keywords: teams,package,pip,MS,Microsoft
Classifier: Programming Language :: Python :: 3
Classifier: License :: OSI Approved :: MIT License
Classifier: Operating System :: OS Independent
Requires-Python: >=3.7
License-File: LICENSE
Requires-Dist: certifi==2024.8.30
Requires-Dist: charset-normalizer==3.3.2
Requires-Dist: idna==3.10
Requires-Dist: requests==2.32.3
Requires-Dist: typing==3.7.4.3
Requires-Dist: urllib3==2.2.3
